anchor/__init__.py
anchor/__main__.py
anchor/_version.py
anchor/command_line.py
anchor/db.py
anchor/main.py
anchor/models.py
anchor/plot.py
anchor/resources_rc.py
anchor/settings.py
anchor/ui_corpus_manager.py
anchor/ui_error_dialog.py
anchor/ui_main_window.py
anchor/ui_preferences.py
anchor/undo.py
anchor/widgets.py
anchor/workers.py
anchor_annotator-0.9.4.dist-info/licenses/LICENSE
anchor_annotator-0.9.4.dist-info/METADATA
anchor_annotator-0.9.4.dist-info/WHEEL
anchor_annotator-0.9.4.dist-info/top_level.txt
anchor_annotator-0.9.4.dist-info/RECORD
