Metadata-Version: 2.4
Name: Anchor_annotator
Version: 0.9.4
Summary: Anchor annotator is a program for inspecting corpora for the Montreal Forced Aligner and correcting transcriptions and pronunciations.
Home-page: https://github.com/MontrealCorpusTools/Anchor-annotator
Author: Montreal Corpus Tools
Author-email: michael.e.mcauliffe@gmail.com
Maintainer: Michael McAuliffe
Maintainer-email: michael.e.mcauliffe@gmail.com
License: MIT
Keywords: phonology,corpus,phonetics,annotation
Classifier: Development Status :: 3 - Alpha
Classifier: License :: OSI Approved :: MIT License
Classifier: Operating System :: OS Independent
Classifier: Programming Language :: Python
Classifier: Programming Language :: Python :: 3
Classifier: Programming Language :: Python :: 3 :: Only
Classifier: Topic :: Multimedia :: Sound/Audio :: Speech
Classifier: Topic :: Scientific/Engineering
Classifier: Topic :: Text Processing :: Linguistic
Requires-Python: >=3.8
License-File: LICENSE
Requires-Dist: montreal-forced-aligner
Requires-Dist: pyqtgraph
Requires-Dist: pyside6
Dynamic: license-file
